silly/__init__.py
silly/main.py
silly-0.0.2.dist-info/DESCRIPTION.rst
silly-0.0.2.dist-info/METADATA
silly-0.0.2.dist-info/RECORD
silly-0.0.2.dist-info/WHEEL
silly-0.0.2.dist-info/metadata.json
silly-0.0.2.dist-info/top_level.txt
