Metadata-Version: 2.0
Name: silly
Version: 0.0.2
Summary: A test data generator that generates stupid names. Like faker, but... silly
Home-page: https://github.com/classam/silly
Author: Curtis Lassam
Author-email: curtis@lassam.net
License: MIT
Requires-Dist: inflect
Requires-Dist: six
Provides-Extra: dev
Provides-Extra: test
